odoo/addons/so_line_product_template_visibility/README.rst
odoo/addons/so_line_product_template_visibility/__init__.py
odoo/addons/so_line_product_template_visibility/__manifest__.py
odoo/addons/so_line_product_template_visibility/static/description/icon.png
odoo/addons/so_line_product_template_visibility/views/sale_order_views.xml
odoo_addon_so_line_product_template_visibility-15.0.1.0.1.dist-info/METADATA
odoo_addon_so_line_product_template_visibility-15.0.1.0.1.dist-info/WHEEL
odoo_addon_so_line_product_template_visibility-15.0.1.0.1.dist-info/top_level.txt
odoo_addon_so_line_product_template_visibility-15.0.1.0.1.dist-info/RECORD
